countach/__init__.py
countach/addressMapping.py
countach/characteristic.py
countach/fileops.py
countach/fixed.py
countach/measurement.py
countach/memorySegment.py
countach/parse.py
countach/types.py
countach-1.1.0.dist-info/LICENSE
countach-1.1.0.dist-info/METADATA
countach-1.1.0.dist-info/WHEEL
countach-1.1.0.dist-info/top_level.txt
countach-1.1.0.dist-info/RECORD
