Metadata-Version: 2.1
Name: countach
Version: 1.1.0
Summary: A library for extracting data from EV2274A A2L files.
Home-page: https://github.com/HWRacing/countach
Author: Hamish Knox
Author-email: hrjkknox@gmail.com
License: MIT
Project-URL: Bug Tracker, https://github.com/HWRacing/countach/issues
Classifier: Programming Language :: Python :: 3
Classifier: Programming Language :: Python :: 3 :: Only
Classifier: Programming Language :: Python :: 3.8
Classifier: Programming Language :: Python :: 3.9
Classifier: Programming Language :: Python :: 3.10
Classifier: Programming Language :: Python :: 3.11
Classifier: License :: OSI Approved :: MIT License
Requires-Python: >=3.8
License-File: LICENSE
Provides-Extra: testing
Requires-Dist: pytest (>=7.0) ; extra == 'testing'
Requires-Dist: tox (>=4.4.0) ; extra == 'testing'
Requires-Dist: mypy (>=1.0.0) ; extra == 'testing'
